pygixml-0.5.0.dist-info/RECORD
pygixml-0.5.0.dist-info/WHEEL
pygixml-0.5.0.dist-info/METADATA
pygixml-0.5.0.dist-info/licenses/LICENSE
include/pugiconfig.hpp
include/pugixml.hpp
lib/libpugixml.a
lib/pkgconfig/pugixml.pc
lib/cmake/pugixml/pugixml-targets.cmake
lib/cmake/pugixml/pugixml-config.cmake
lib/cmake/pugixml/pugixml-config-version.cmake
lib/cmake/pugixml/pugixml-targets-release.cmake
pygixml/pygixml.pyx
pygixml/__init__.py
pygixml/pygixml.pypy39-pp73-darwin.so
