Metadata-Version: 2.2
Name: pygixml
Version: 0.5.0
Summary: Python wrapper for pugixml using Cython - Please star the project on GitHub to use!
Keywords: xml,pugixml,cython,wrapper
Author-Email: Mohammad Raziei <mohammadraziei1375@gmail.com>
License: MIT License
Classifier: Development Status :: 3 - Alpha
Classifier: Intended Audience :: Developers
Classifier: License :: OSI Approved :: MIT License
Classifier: Programming Language :: Python :: 3
Classifier: Programming Language :: Python :: 3.8
Classifier: Programming Language :: Python :: 3.9
Classifier: Programming Language :: Python :: 3.10
Classifier: Programming Language :: Python :: 3.11
Classifier: Programming Language :: Python :: 3.12
Project-URL: Homepage, https://github.com/mohammadraziei/pygixml
Project-URL: Bug Tracker, https://github.com/mohammadraziei/pygixml/issues
Project-URL: Document, https://mohammadraziei.github.io/pygixml
Requires-Python: >=3.8
Provides-Extra: test
Requires-Dist: pytest>=7.0.0; extra == "test"
Requires-Dist: pytest-xdist>=3.0.0; extra == "test"
Requires-Dist: pytest-timeout>=2.0.0; extra == "test"
